{
    "greeting": "Hy 👋",
    "name": "Mba Sischa",
    "greetingText": "I really like your voice & the way you smile, btw!",
    "wishText": "I wish you're enjoying your special day yah! ;)",
    "imagePath": "./img/profile.jpg",
    "text1": "Today is your birthday Mba!!! :D",
    "textInChatBox": "Yaumul milad Mba Sischa, barakallah fii umrik blah.. blah...",
    "sendButtonLabel": "Send",
    "text2": "That's what I was going to do.",
    "text3": "Tapi aku berhenti Mba.",
    "text4": "I realised, I wanted to do something",
    "text4Adjective": "Special",
    "text5Entry": "Karena,",
    "text5Content": "Kamu itu Special Mba!",
    "smiley": ":)",
    "text6Content": "That's why I made this website for you",
    "bigTextPart1": "S",
    "bigTextPart2": "O",
    "wishHeading": "Happy Birthday Galuh Sischa",
    "outroText": "Okay, now come back and tell me if you liked it.",
    "replayText": "Or click this, kalau kamu mau lihat dari awal lagi.",
    "outroSmiley": ":)"
  }